Metadata-Version: 1.1
Name: keras-network-practice
Version: 1.0.3
Summary: this is a test package for packing python liberaries tutorial.
Home-page: https://github.com
Author: echocheng
Author-email: jing_cheng1103@163.com
License: MIT License
Keywords: test python package
Platform: UNKNOWN
Classifier: License :: OSI Approved :: MIT License
Classifier: Programming Language :: Python
Classifier: Intended Audience :: Developers
Classifier: Operating System :: OS Independent
